LICENSE.txt
README.txt
buildout.cfg
setup.py
src/zc/__init__.py
src/zc.signalhandler.egg-info/PKG-INFO
src/zc.signalhandler.egg-info/SOURCES.txt
src/zc.signalhandler.egg-info/dependency_links.txt
src/zc.signalhandler.egg-info/namespace_packages.txt
src/zc.signalhandler.egg-info/not-zip-safe
src/zc.signalhandler.egg-info/requires.txt
src/zc.signalhandler.egg-info/top_level.txt
src/zc/signalhandler/README.txt
src/zc/signalhandler/__init__.py
src/zc/signalhandler/component.xml
src/zc/signalhandler/datatypes.py
src/zc/signalhandler/tests.py