Metadata-Version: 1.0
Name: zc.signalhandler
Version: 1.2.0
Summary: Configurable signal handling for ZConfig
Home-page: UNKNOWN
Author: Zope Corporation
Author-email: info@zope.com
License: ZPL 2.1
Platform: UNKNOWN
